gnuplot_manager/__init__.py
gnuplot_manager/classes.py
gnuplot_manager/demo.py
gnuplot_manager/errors.py
gnuplot_manager/functions.py
gnuplot_manager/funcutils.py
gnuplot_manager/global_variables.py
gnuplot_manager/test.py
gnuplot_manager-0.1.8.dist-info/LICENSE.txt
gnuplot_manager-0.1.8.dist-info/METADATA
gnuplot_manager-0.1.8.dist-info/WHEEL
gnuplot_manager-0.1.8.dist-info/top_level.txt
gnuplot_manager-0.1.8.dist-info/RECORD
