Metadata-Version: 2.1
Name: gnuplot_manager
Version: 0.1.8
Summary: A manager to symplify the use of gnuplot inside python
Home-page: https://github.com/pietromandracci/gnuplot_manager
Author: Pietro Mandracci
Author-email: pietro.mandracci.software@gmail.com
Classifier: Programming Language :: Python :: 3
Classifier: License :: OSI Approved :: GNU General Public License v3 or later (GPLv3+)
Classifier: Operating System :: POSIX :: Linux
Requires-Python: >=3
License-File: LICENSE.txt
